LICENSE
MANIFEST.in
README.md
requirements.txt
setup.cfg
setup.py
versioneer.py
botcity/core/__init__.py
botcity/core/_version.py
botcity/core/bot.py
botcity/core/config.py
botcity/core/cv2find.py
botcity/core/os_compat.py
botcity/core/utils.py
botcity/core/application/__init__.py
botcity/core/application/functions.py
botcity/core/application/utils.py
botcity/core/tests/__init__.py
botcity/core/tests/test_import.py
botcity_framework_core.egg-info/PKG-INFO
botcity_framework_core.egg-info/SOURCES.txt
botcity_framework_core.egg-info/dependency_links.txt
botcity_framework_core.egg-info/requires.txt
botcity_framework_core.egg-info/top_level.txt