Metadata-Version: 2.1
Name: botcity-framework-core
Version: 0.4.0
Home-page: https://www.github.com/botcity-dev/botcity-framework-core-python
Requires-Python: >=3.7
License-File: LICENSE
